Metadata-Version: 1.0
Name: nwscan
Version: 0.3
Summary: Scan networks for alive hosts
Home-page: https://github.com/pdrb/nwscan
Author: Pedro Buteri Gonring
Author-email: pedro@bigode.net
License: MIT
Keywords: scan scanner network networks ip ips host hosts alive nwscan
Platform: UNKNOWN
